README.md
setup.py
juc2/__init__.py
juc2/stage.py
juc2.egg-info/PKG-INFO
juc2.egg-info/SOURCES.txt
juc2.egg-info/dependency_links.txt
juc2.egg-info/top_level.txt
juc2/art/__init__.py
juc2/art/animals.py
juc2/art/meta.py
juc2/art/objects.py
juc2/art/shapes.py
juc2/art/symbols.py
juc2/art/tools.py